mobilitydb/__init__.py
mobilitydb/asyncpg.py
mobilitydb/psycopg.py
mobilitydb/boxes/__init__.py
mobilitydb/boxes/stbox.py
mobilitydb/boxes/tbox.py
mobilitydb/examples/__init__.py
mobilitydb/examples/box.py
mobilitydb/examples/box_asyncpg.py
mobilitydb/examples/box_psycopg.py
mobilitydb/examples/db_connect.py
mobilitydb/examples/tbool.py
mobilitydb/examples/tbool_asyncpg.py
mobilitydb/examples/tbool_psycopg.py
mobilitydb/examples/tfloat.py
mobilitydb/examples/tfloat_asyncpg.py
mobilitydb/examples/tfloat_psycopg.py
mobilitydb/examples/tgeogpoint.py
mobilitydb/examples/tgeogpoint_asyncpg.py
mobilitydb/examples/tgeogpoint_psycopg.py
mobilitydb/examples/tgeompoint.py
mobilitydb/examples/tgeompoint_asyncpg.py
mobilitydb/examples/tgeompoint_psycopg.py
mobilitydb/examples/time.py
mobilitydb/examples/time_asyncpg.py
mobilitydb/examples/time_psycopg.py
mobilitydb/examples/tint.py
mobilitydb/examples/tint_asyncpg.py
mobilitydb/examples/tint_psycopg.py
mobilitydb/examples/ttext.py
mobilitydb/examples/ttext_asyncpg.py
mobilitydb/examples/ttext_psycopg.py
mobilitydb/main/__init__.py
mobilitydb/main/tbool.py
mobilitydb/main/tfloat.py
mobilitydb/main/tint.py
mobilitydb/main/tpoint.py
mobilitydb/main/ttext.py
mobilitydb/temporal/__init__.py
mobilitydb/temporal/temporal.py
mobilitydb/temporal/temporal_parser.py
mobilitydb/temporal/temporalinstants.py
mobilitydb/temporal/tinstant.py
mobilitydb/temporal/tinstantset.py
mobilitydb/temporal/tsequence.py
mobilitydb/temporal/tsequenceset.py
mobilitydb/time/__init__.py
mobilitydb/time/period.py
mobilitydb/time/periodset.py
mobilitydb/time/timestampset.py
tests/__init__.py
tests/asyncpg/__init__.py
tests/asyncpg/conftest.py
tests/asyncpg/test_stbox.py
tests/asyncpg/test_tbool.py
tests/asyncpg/test_tbox.py
tests/asyncpg/test_tfloat.py
tests/asyncpg/test_tgeogpoint.py
tests/asyncpg/test_tgeompoint.py
tests/asyncpg/test_time.py
tests/asyncpg/test_tint.py
tests/asyncpg/test_ttext.py
tests/psycopg/__init__.py
tests/psycopg/conftest.py
python_mobilitydb-0.1.3.dist-info/METADATA
python_mobilitydb-0.1.3.dist-info/WHEEL
python_mobilitydb-0.1.3.dist-info/top_level.txt
python_mobilitydb-0.1.3.dist-info/RECORD
