Metadata-Version: 2.1
Name: python-mobilitydb
Version: 0.1.3
Summary: A database adapter to access MobilityDB from Python
Home-page: https://github.com/MobilityDB/MobilityDB-python
Download-URL: 
Author: MobilityDB Project
License: MIT
Project-URL: Source, https://github.com/MobilityDB/MobilityDB-python
Project-URL: Documentation, https://docs.mobilitydb.com/MobilityDB-python/master/python-mobilitydb.pdf
Keywords: MobilityDB,Python
Platform: linux
Classifier: Development Status :: 3 - Alpha
Classifier: Intended Audience :: Developers
Classifier: Topic :: Database :: Front-Ends
Classifier: Topic :: Software Development :: Libraries :: Python Modules
Classifier: Topic :: Scientific/Engineering :: GIS
Classifier: License :: OSI Approved :: MIT License
Classifier: Programming Language :: Python :: 3
Classifier: Programming Language :: Python :: 3.4
Classifier: Programming Language :: Python :: 3.5
Classifier: Programming Language :: Python :: 3.6
Classifier: Programming Language :: Python :: 3.7
Classifier: Programming Language :: Python :: 3.8
Classifier: Programming Language :: Python :: 3.9
Requires-Dist: asyncpg
Requires-Dist: psycopg2-binary
Requires-Dist: Spans
Requires-Dist: postgis
Requires-Dist: pytest
Requires-Dist: python-dateutil
Requires-Dist: parsec
Requires-Dist: pytest-asyncio
